.gitignore
CHANGELOG.md
LICENSE.txt
README.md
TODO.md
requirements.txt
setup.cfg
setup.py
bin/jiraprompt
jiraprompt/__init__.py
jiraprompt/common.py
jiraprompt/main.py
jiraprompt/prompt.py
jiraprompt/res.py
jiraprompt/resource_collections.py
jiraprompt/wrapper.py
jiraprompt.egg-info/PKG-INFO
jiraprompt.egg-info/SOURCES.txt
jiraprompt.egg-info/dependency_links.txt
jiraprompt.egg-info/requires.txt
jiraprompt.egg-info/top_level.txt
jiraprompt/resources/ascii_art.txt
jiraprompt/resources/config_default.yml
jiraprompt/resources/issue_template.yml
jiraprompt/resources/labels_default.yml
jiraprompt/utils/__init__.py
jiraprompt/utils/update_check.py