Metadata-Version: 1.2
Name: jiraprompt
Version: 0.0.4
Summary: simplifies agile workflows for jira boards using a cli-based prompt
Home-page: https://www.github.com/bsquizz/jiraprompt
Author: Brandon Squizzato
Author-email: bsquizza@redhat.com
License: MIT
Keywords: jira,agile
Platform: UNKNOWN
Classifier: Topic :: Utilities
Classifier: License :: OSI Approved :: MIT License
Classifier: Programming Language :: Python
Classifier: Programming Language :: Python :: 2
Classifier: Programming Language :: Python :: 3
Classifier: Programming Language :: Python :: 2.7
Classifier: Programming Language :: Python :: 3.4
Classifier: Programming Language :: Python :: 3.5
Classifier: Programming Language :: Python :: 3.6
Requires-Python: >=2.7, !=3.0.*, !=3.1.*, !=3.2.*, !=3.3.*
